{
    "_links":{
        "next":{
            "href":"https://test.moip.com.br/v2/orders?filters=&limit=0&offset=0"
        },
        "previous":{
            "href":"https://test.moip.com.br/v2/orders?filters=&limit=0&offset=0"
        }
    },
    "summary":{
        "count":4,
        "amount":1113856575
    },
    "orders":[
              {
              "id":"ORD-FG3KSL7WIY3T",
              "ownId":"1508952182",
              "status":"PAID",
              "blocked":false,
              "amount":{
              "total":30501250,
              "addition":0,
              "fees":0,
              "deduction":0,
              "otherReceivers":0,
              "currency":"BRL"
              },
              "receivers":[
                           {
                           "type":"PRIMARY",
                           "moipAccount":{
                           "id":"MPA-B4DEE9F7589B"
                           }
                           }
                           ],
              "customer":{
              "fullname":"authorize",
              "email":"nome1508952182@email.com"
              },
              "items":[
                       {
                       "product":null
                       }
                       ],
              "payments":[
                          {
                          "id":"PAY-G0FQUN2CBDNY",
                          "installmentCount":1,
                          "fundingInstrument":{
                          "method":"CREDIT_CARD",
                          "brand":"MASTERCARD"
                          }
                          }
                          ],
              "events":[
                        {
                        "type":"PAYMENT.AUTHORIZED",
                        "createdAt":"2017-10-25T15:24:00Z"
                        }
                        ],
              "_links":{
              "self":{
              "href":"https://test.moip.com.br/v2/orders/ORD-FG3KSL7WIY3T"
              }
              },
              "createdAt":"2017-10-25T15:23:02-0300",
              "updatedAt":"2017-10-25T15:25:49-0300"
              },
              {
              "id":"ORD-CJAHRCVUYTHH",
              "ownId":"1508951687",
              "status":"PAID",
              "blocked":false,
              "amount":{
              "total":30501250,
              "addition":0,
              "fees":0,
              "deduction":0,
              "otherReceivers":0,
              "currency":"BRL"
              },
              "receivers":[
                           {
                           "type":"PRIMARY",
                           "moipAccount":{
                           "id":"MPA-B4DEE9F7589B"
                           }
                           }
                           ],
              "customer":{
              "fullname":"authorize",
              "email":"nome1508951687@email.com"
              },
              "items":[
                       {
                       "product":null
                       }
                       ],
              "payments":[
                          {
                          "id":"PAY-GRKWEOIR75MB",
                          "installmentCount":1,
                          "fundingInstrument":{
                          "method":"CREDIT_CARD",
                          "brand":"MASTERCARD"
                          }
                          }
                          ],
              "events":[
                        {
                        "type":"PAYMENT.AUTHORIZED",
                        "createdAt":"2017-10-25T15:15:45Z"
                        }
                        ],
              "_links":{
              "self":{
              "href":"https://test.moip.com.br/v2/orders/ORD-CJAHRCVUYTHH"
              }
              },
              "createdAt":"2017-10-25T15:14:46-0300",
              "updatedAt":"2017-10-25T15:15:45-0300"
              },
              {
              "id":"ORD-4UD06KERSPTF",
              "ownId":"1508951570",
              "status":"PAID",
              "blocked":false,
              "amount":{
              "total":30501250,
              "addition":0,
              "fees":0,
              "deduction":0,
              "otherReceivers":0,
              "currency":"BRL"
              },
              "receivers":[
                           {
                           "type":"PRIMARY",
                           "moipAccount":{
                           "id":"MPA-B4DEE9F7589B"
                           }
                           }
                           ],
              "customer":{
              "fullname":"authorize",
              "email":"nome1508951570@email.com"
              },
              "items":[
                       {
                       "product":null
                       }
                       ],
              "payments":[
                          {
                          "id":"PAY-GXSDKZ83DF3N",
                          "installmentCount":1,
                          "fundingInstrument":{
                          "method":"CREDIT_CARD",
                          "brand":"MASTERCARD"
                          }
                          }
                          ],
              "events":[
                        {
                        "type":"PAYMENT.AUTHORIZED",
                        "createdAt":"2017-10-25T15:13:53Z"
                        }
                        ],
              "_links":{
              "self":{
              "href":"https://test.moip.com.br/v2/orders/ORD-4UD06KERSPTF"
              }
              },
              "createdAt":"2017-10-25T15:12:50-0300",
              "updatedAt":"2017-10-25T15:13:53-0300"
              },
              {
              "id":"ORD-D7OWF7PYGDQN",
              "ownId":"1508951546",
              "status":"PAID",
              "blocked":false,
              "amount":{
              "total":30501250,
              "addition":0,
              "fees":0,
              "deduction":0,
              "otherReceivers":0,
              "currency":"BRL"
              },
              "receivers":[
                           {
                           "type":"PRIMARY",
                           "moipAccount":{
                           "id":"MPA-B4DEE9F7589B"
                           }
                           }
                           ],
              "customer":{
              "fullname":"authorize",
              "email":"nome1508951546@email.com"
              },
              "items":[
                       {
                       "product":null
                       }
                       ],
              "payments":[
                          {
                          "id":"PAY-I523GB424MRL",
                          "installmentCount":1,
                          "fundingInstrument":{
                          "method":"CREDIT_CARD",
                          "brand":"MASTERCARD"
                          }
                          }
                          ],
              "events":[
                        {
                        "type":"PAYMENT.AUTHORIZED",
                        "createdAt":"2017-10-25T15:13:17Z"
                        }
                        ],
              "_links":{
              "self":{
              "href":"https://test.moip.com.br/v2/orders/ORD-D7OWF7PYGDQN"
              }
              },
              "createdAt":"2017-10-25T15:12:26-0300",
              "updatedAt":"2017-10-25T15:13:17-0300"
              }
              ]
}
